[{"entrance":"2019-07-04T17:48:51Z","status":"paid","totalCharge":"IDR28000","user":{"$oid":"5d1cb531fc13ae46290001ab"},"licencePlate":"B3188WVB","Number":"A67"},{"entrance":"2019-07-04T16:57:47Z","status":"waiting","totalCharge":"0","user":{"$oid":"5d1cb531fc13ae46290001cb"},"licencePlate":"B2172PST","Number":"A99"},{"entrance":"2019-07-04T16:26:33Z","status":"waiting","totalCharge":"0","user":{"$oid":"5d1cb531fc13ae46290001d0"},"licencePlate":"B4068RKM","Number":"B4"},{"entrance":"2019-07-04T14:53:05Z","status":"paid","totalCharge":"IDR97000","user":{"$oid":"5d1cb531fc13ae46290001dc"},"licencePlate":"B7285ETR","Number":"B16"},{"entrance":"2019-07-04T14:52:46Z","status":"waiting","totalCharge":"0","user":{"$oid":"5d1cb531fc13ae46290001e5"},"licencePlate":"B0233MDZ","Number":"B25"},{"entrance":"2019-07-04T11:54:08Z","status":"waiting","totalCharge":"0","user":{"$oid":"5d1cb531fc13ae462900021a"},"licencePlate":"B4657SKJ","Number":"B78"},{"entrance":"2019-07-04T09:49:58Z","status":"waiting","totalCharge":"0","user":{"$oid":"5d1cb530fc13ae4629000181"},"licencePlate":"B0711TCH","Number":"A25"},{"entrance":"2019-07-04T05:00:32Z","status":"paid","totalCharge":"IDR33000","user":{"$oid":"5d1cb531fc13ae46290001b9"},"licencePlate":"B2054YZF","Number":"A81"},{"entrance":"2019-07-04T03:49:46Z","status":"canceled","totalCharge":"-","user":{"$oid":"5d1cb530fc13ae462900017d"},"licencePlate":"B0524ARV","Number":"A21"},{"entrance":"2019-07-04T03:36:16Z","status":"waiting","totalCharge":"0","user":{"$oid":"5d1cb531fc13ae46290001b8"},"licencePlate":"B8610GZS","Number":"A80"},{"entrance":"2019-07-04T02:45:12Z","status":"paid","totalCharge":"IDR90000","user":{"$oid":"5d1cb531fc13ae4629000208"},"licencePlate":"B0211VGT","Number":"B60"},{"entrance":"2019-07-04T02:24:29Z","status":"canceled","totalCharge":"-","user":{"$oid":"5d1cb531fc13ae46290001f6"},"licencePlate":"B7403IHQ","Number":"B42"},{"entrance":"2019-07-03T23:24:56Z","status":"canceled","totalCharge":"-","user":{"$oid":"5d1cb531fc13ae462900018d"},"licencePlate":"B5083VIZ","Number":"A37"},{"entrance":"2019-07-03T22:31:08Z","status":"waiting","totalCharge":"0","user":{"$oid":"5d1cb531fc13ae46290001d3"},"licencePlate":"B6347QBE","Number":"B7"},{"entrance":"2019-07-03T19:21:17Z","status":"canceled","totalCharge":"-","user":{"$oid":"5d1cb531fc13ae46290001dd"},"licencePlate":"B2861NTS","Number":"B17"},{"entrance":"2019-07-03T18:08:38Z","status":"paid","totalCharge":"IDR44000","user":{"$oid":"5d1cb531fc13ae46290001e3"},"licencePlate":"B5302MLQ","Number":"B23"},{"entrance":"2019-07-03T16:00:52Z","status":"paid","totalCharge":"IDR22000","user":{"$oid":"5d1cb530fc13ae4629000171"},"licencePlate":"B4011AYA","Number":"A9"},{"entrance":"2019-07-03T14:26:54Z","status":"waiting","totalCharge":"0","user":{"$oid":"5d1cb531fc13ae4629000190"},"licencePlate":"B7421MPC","Number":"A40"},{"entrance":"2019-07-03T13:08:57Z","status":"waiting","totalCharge":"0","user":{"$oid":"5d1cb531fc13ae46290001a9"},"licencePlate":"B6752IDE","Number":"A65"},{"entrance":"2019-07-03T11:56:15Z","status":"paid","totalCharge":"IDR58000","user":{"$oid":"5d1cb531fc13ae46290001b6"},"licencePlate":"B3437LHP","Number":"A78"},{"entrance":"2019-07-03T09:23:48Z","status":"paid","totalCharge":"IDR20000","user":{"$oid":"5d1cb531fc13ae46290001de"},"licencePlate":"B4863ZIV","Number":"B18"},{"entrance":"2019-07-03T07:48:15Z","status":"paid","totalCharge":"IDR100000","user":{"$oid":"5d1cb530fc13ae4629000178"},"licencePlate":"B5356ZPS","Number":"A16"},{"entrance":"2019-07-03T07:33:33Z","status":"paid","totalCharge":"IDR90000","user":{"$oid":"5d1cb531fc13ae46290001fd"},"licencePlate":"B4345DME","Number":"B49"},{"entrance":"2019-07-03T07:30:41Z","status":"canceled","totalCharge":"-","user":{"$oid":"5d1cb531fc13ae46290001e4"},"licencePlate":"B5277PYF","Number":"B24"},{"entrance":"2019-07-03T07:29:30Z","status":"waiting","totalCharge":"0","user":{"$oid":"5d1cb531fc13ae4629000196"},"licencePlate":"B8264LNT","Number":"A46"},{"entrance":"2019-07-03T07:23:10Z","status":"canceled","totalCharge":"-","user":{"$oid":"5d1cb531fc13ae4629000200"},"licencePlate":"B1831ABG","Number":"B52"},{"entrance":"2019-07-03T03:31:16Z","status":"paid","totalCharge":"IDR75000","user":{"$oid":"5d1cb531fc13ae4629000201"},"licencePlate":"B5888ZQG","Number":"B53"},{"entrance":"2019-07-03T03:27:50Z","status":"waiting","totalCharge":"0","user":{"$oid":"5d1cb531fc13ae46290001b7"},"licencePlate":"B8046KTJ","Number":"A79"},{"entrance":"2019-07-02T23:16:55Z","status":"paid","totalCharge":"IDR69000","user":{"$oid":"5d1cb531fc13ae46290001c5"},"licencePlate":"B3816TLX","Number":"A93"},{"entrance":"2019-07-02T21:39:32Z","status":"canceled","totalCharge":"-","user":{"$oid":"5d1cb531fc13ae46290001c0"},"licencePlate":"B0508CKE","Number":"A88"},{"entrance":"2019-07-02T18:41:27Z","status":"canceled","totalCharge":"-","user":{"$oid":"5d1cb530fc13ae462900016a"},"licencePlate":"B3678AAT","Number":"A2"},{"entrance":"2019-07-02T16:01:51Z","status":"canceled","totalCharge":"-","user":{"$oid":"5d1cb531fc13ae46290001df"},"licencePlate":"B2450DXV","Number":"B19"},{"entrance":"2019-07-02T14:42:46Z","status":"canceled","totalCharge":"-","user":{"$oid":"5d1cb531fc13ae46290001b4"},"licencePlate":"B2571VQX","Number":"A76"},{"entrance":"2019-07-02T12:10:11Z","status":"canceled","totalCharge":"-","user":{"$oid":"5d1cb531fc13ae46290001d4"},"licencePlate":"B3030QZC","Number":"B8"},{"entrance":"2019-07-02T08:04:04Z","status":"paid","totalCharge":"IDR24000","user":{"$oid":"5d1cb531fc13ae4629000214"},"licencePlate":"B6528MYH","Number":"B72"},{"entrance":"2019-07-02T07:56:06Z","status":"canceled","totalCharge":"-","user":{"$oid":"5d1cb530fc13ae4629000188"},"licencePlate":"B6217FPS","Number":"A32"},{"entrance":"2019-07-02T05:37:44Z","status":"paid","totalCharge":"IDR77000","user":{"$oid":"5d1cb531fc13ae46290001c4"},"licencePlate":"B2346PPN","Number":"A92"},{"entrance":"2019-07-02T05:21:40Z","status":"paid","totalCharge":"IDR90000","user":{"$oid":"5d1cb531fc13ae46290001ea"},"licencePlate":"B7135MNQ","Number":"B30"},{"entrance":"2019-07-02T04:27:57Z","status":"canceled","totalCharge":"-","user":{"$oid":"5d1cb531fc13ae46290001a4"},"licencePlate":"B8433LDQ","Number":"A60"},{"entrance":"2019-07-02T03:23:56Z","status":"canceled","totalCharge":"-","user":{"$oid":"5d1cb531fc13ae4629000218"},"licencePlate":"B5846NSK","Number":"B76"},{"entrance":"2019-07-02T02:30:39Z","status":"waiting","totalCharge":"0","user":{"$oid":"5d1cb530fc13ae4629000185"},"licencePlate":"B4546FZO","Number":"A29"},{"entrance":"2019-07-01T19:56:18Z","status":"paid","totalCharge":"IDR65000","user":{"$oid":"5d1cb531fc13ae462900018c"},"licencePlate":"B5082ESE","Number":"A36"},{"entrance":"2019-07-01T19:46:14Z","status":"paid","totalCharge":"IDR76000","user":{"$oid":"5d1cb531fc13ae46290001bd"},"licencePlate":"B7016WQV","Number":"A85"},{"entrance":"2019-07-01T19:41:08Z","status":"canceled","totalCharge":"-","user":{"$oid":"5d1cb530fc13ae4629000189"},"licencePlate":"B8381TYM","Number":"A33"},{"entrance":"2019-07-01T18:50:25Z","status":"canceled","totalCharge":"-","user":{"$oid":"5d1cb531fc13ae46290001cd"},"licencePlate":"B2875ZIY","Number":"B1"},{"entrance":"2019-07-01T18:17:13Z","status":"paid","totalCharge":"IDR68000","user":{"$oid":"5d1cb531fc13ae46290001ee"},"licencePlate":"B2827HGW","Number":"B34"},{"entrance":"2019-07-01T18:11:49Z","status":"canceled","totalCharge":"-","user":{"$oid":"5d1cb531fc13ae462900019b"},"licencePlate":"B4032XIH","Number":"A51"},{"entrance":"2019-07-01T16:15:44Z","status":"waiting","totalCharge":"0","user":{"$oid":"5d1cb531fc13ae46290001af"},"licencePlate":"B0435WSK","Number":"A71"},{"entrance":"2019-07-01T16:06:01Z","status":"waiting","totalCharge":"0","user":{"$oid":"5d1cb531fc13ae46290001f8"},"licencePlate":"B2881YVR","Number":"B44"},{"entrance":"2019-07-01T14:41:37Z","status":"paid","totalCharge":"IDR83000","user":{"$oid":"5d1cb531fc13ae46290001bb"},"licencePlate":"B3476HFK","Number":"A83"},{"entrance":"2019-07-01T13:13:53Z","status":"paid","totalCharge":"IDR95000","user":{"$oid":"5d1cb531fc13ae46290001f0"},"licencePlate":"B2306JGI","Number":"B36"},{"entrance":"2019-07-01T11:35:59Z","status":"waiting","totalCharge":"0","user":{"$oid":"5d1cb530fc13ae4629000169"},"licencePlate":"B7758YCE","Number":"A1"},{"entrance":"2019-07-01T11:30:50Z","status":"waiting","totalCharge":"0","user":{"$oid":"5d1cb531fc13ae46290001a7"},"licencePlate":"B1635CTE","Number":"A63"},{"entrance":"2019-07-01T09:42:52Z","status":"paid","totalCharge":"IDR82000","user":{"$oid":"5d1cb531fc13ae462900019c"},"licencePlate":"B2006IKL","Number":"A52"},{"entrance":"2019-07-01T09:21:17Z","status":"canceled","totalCharge":"-","user":{"$oid":"5d1cb530fc13ae462900016d"},"licencePlate":"B7172JOV","Number":"A5"},{"entrance":"2019-07-01T06:14:32Z","status":"paid","totalCharge":"IDR85000","user":{"$oid":"5d1cb531fc13ae46290001ed"},"licencePlate":"B6481ZZN","Number":"B33"},{"entrance":"2019-07-01T05:45:01Z","status":"canceled","totalCharge":"-","user":{"$oid":"5d1cb531fc13ae46290001ba"},"licencePlate":"B6443FHF","Number":"A82"},{"entrance":"2019-07-01T05:29:52Z","status":"paid","totalCharge":"IDR84000","user":{"$oid":"5d1cb531fc13ae46290001aa"},"licencePlate":"B2253JEN","Number":"A66"},{"entrance":"2019-07-01T03:12:50Z","status":"paid","totalCharge":"IDR64000","user":{"$oid":"5d1cb531fc13ae46290001d7"},"licencePlate":"B7057BAM","Number":"B11"},{"entrance":"2019-07-01T03:10:29Z","status":"canceled","totalCharge":"-","user":{"$oid":"5d1cb531fc13ae46290001e6"},"licencePlate":"B2237WWM","Number":"B26"},{"entrance":"2019-07-01T00:38:02Z","status":"paid","totalCharge":"IDR72000","user":{"$oid":"5d1cb531fc13ae46290001b5"},"licencePlate":"B1651BEO","Number":"A77"},{"entrance":"2019-07-01T00:33:52Z","status":"canceled","totalCharge":"-","user":{"$oid":"5d1cb531fc13ae4629000219"},"licencePlate":"B8205JYE","Number":"B77"},{"entrance":"2019-07-01T00:29:17Z","status":"paid","totalCharge":"IDR92000","user":{"$oid":"5d1cb531fc13ae46290001f5"},"licencePlate":"B6045ZQX","Number":"B41"},{"entrance":"2019-07-01T00:17:51Z","status":"waiting","totalCharge":"0","user":{"$oid":"5d1cb531fc13ae4629000210"},"licencePlate":"B3885KCQ","Number":"B68"},{"entrance":"2019-07-01T00:04:00Z","status":"paid","totalCharge":"IDR92000","user":{"$oid":"5d1cb531fc13ae46290001e9"},"licencePlate":"B3524KLY","Number":"B29"},{"entrance":"2019-06-30T23:37:11Z","status":"canceled","totalCharge":"-","user":{"$oid":"5d1cb531fc13ae46290001bc"},"licencePlate":"B8863AFX","Number":"A84"},{"entrance":"2019-06-30T21:38:20Z","status":"canceled","totalCharge":"-","user":{"$oid":"5d1cb531fc13ae46290001b0"},"licencePlate":"B0522TFI","Number":"A72"},{"entrance":"2019-06-30T19:21:14Z","status":"paid","totalCharge":"IDR82000","user":{"$oid":"5d1cb530fc13ae462900016b"},"licencePlate":"B0247CFC","Number":"A3"},{"entrance":"2019-06-30T18:36:26Z","status":"canceled","totalCharge":"-","user":{"$oid":"5d1cb531fc13ae46290001a1"},"licencePlate":"B4167DJH","Number":"A57"},{"entrance":"2019-06-30T17:36:03Z","status":"canceled","totalCharge":"-","user":{"$oid":"5d1cb531fc13ae46290001d1"},"licencePlate":"B6356OPA","Number":"B5"},{"entrance":"2019-06-30T15:52:15Z","status":"waiting","totalCharge":"0","user":{"$oid":"5d1cb531fc13ae46290001d9"},"licencePlate":"B5265ADI","Number":"B13"},{"entrance":"2019-06-30T10:03:33Z","status":"canceled","totalCharge":"-","user":{"$oid":"5d1cb531fc13ae4629000217"},"licencePlate":"B7113FYY","Number":"B75"},{"entrance":"2019-06-30T08:30:05Z","status":"waiting","totalCharge":"0","user":{"$oid":"5d1cb531fc13ae46290001a2"},"licencePlate":"B1070MJA","Number":"A58"},{"entrance":"2019-06-30T06:44:32Z","status":"waiting","totalCharge":"0","user":{"$oid":"5d1cb531fc13ae46290001f9"},"licencePlate":"B1673EBR","Number":"B45"},{"entrance":"2019-06-30T05:25:39Z","status":"waiting","totalCharge":"0","user":{"$oid":"5d1cb531fc13ae46290001fb"},"licencePlate":"B7648MFX","Number":"B47"},{"entrance":"2019-06-30T05:21:15Z","status":"waiting","totalCharge":"0","user":{"$oid":"5d1cb530fc13ae4629000172"},"licencePlate":"B8666EXS","Number":"A10"},{"entrance":"2019-06-30T04:25:02Z","status":"waiting","totalCharge":"0","user":{"$oid":"5d1cb531fc13ae46290001ae"},"licencePlate":"B8041NIV","Number":"A70"},{"entrance":"2019-06-30T02:57:22Z","status":"canceled","totalCharge":"-","user":{"$oid":"5d1cb531fc13ae462900020d"},"licencePlate":"B8040RBM","Number":"B65"},{"entrance":"2019-06-29T23:09:03Z","status":"waiting","totalCharge":"0","user":{"$oid":"5d1cb531fc13ae46290001e7"},"licencePlate":"B8740NMG","Number":"B27"},{"entrance":"2019-06-29T20:05:39Z","status":"canceled","totalCharge":"-","user":{"$oid":"5d1cb530fc13ae4629000177"},"licencePlate":"B4032ABA","Number":"A15"},{"entrance":"2019-06-29T17:50:44Z","status":"waiting","totalCharge":"0","user":{"$oid":"5d1cb530fc13ae4629000184"},"licencePlate":"B0303IYT","Number":"A28"},{"entrance":"2019-06-29T09:03:36Z","status":"canceled","totalCharge":"-","user":{"$oid":"5d1cb531fc13ae46290001a0"},"licencePlate":"B8570LJE","Number":"A56"},{"entrance":"2019-06-29T08:42:39Z","status":"waiting","totalCharge":"0","user":{"$oid":"5d1cb531fc13ae46290001ca"},"licencePlate":"B1051PMB","Number":"A98"},{"entrance":"2019-06-29T03:39:03Z","status":"canceled","totalCharge":"-","user":{"$oid":"5d1cb531fc13ae46290001c8"},"licencePlate":"B0086KDP","Number":"A96"},{"entrance":"2019-06-28T22:15:27Z","status":"paid","totalCharge":"IDR41000","user":{"$oid":"5d1cb531fc13ae46290001cc"},"licencePlate":"B8254CCI","Number":"A100"},{"entrance":"2019-06-28T20:13:31Z","status":"paid","totalCharge":"IDR48000","user":{"$oid":"5d1cb531fc13ae462900018f"},"licencePlate":"B5484KLF","Number":"A39"},{"entrance":"2019-06-28T19:38:34Z","status":"paid","totalCharge":"IDR93000","user":{"$oid":"5d1cb531fc13ae462900020e"},"licencePlate":"B6116KXW","Number":"B66"},{"entrance":"2019-06-28T18:33:06Z","status":"waiting","totalCharge":"0","user":{"$oid":"5d1cb531fc13ae4629000213"},"licencePlate":"B0273AHQ","Number":"B71"},{"entrance":"2019-06-28T18:25:51Z","status":"waiting","totalCharge":"0","user":{"$oid":"5d1cb530fc13ae462900017a"},"licencePlate":"B1638EOM","Number":"A18"},{"entrance":"2019-06-28T17:59:38Z","status":"paid","totalCharge":"IDR62000","user":{"$oid":"5d1cb531fc13ae462900019e"},"licencePlate":"B1816PEP","Number":"A54"},{"entrance":"2019-06-28T17:31:10Z","status":"canceled","totalCharge":"-","user":{"$oid":"5d1cb530fc13ae4629000168"},"licencePlate":"B6242PNF","Number":"A0"},{"entrance":"2019-06-28T15:21:44Z","status":"paid","totalCharge":"IDR81000","user":{"$oid":"5d1cb531fc13ae46290001e8"},"licencePlate":"B7030ZXQ","Number":"B28"},{"entrance":"2019-06-28T12:56:33Z","status":"waiting","totalCharge":"0","user":{"$oid":"5d1cb530fc13ae462900017c"},"licencePlate":"B7641NRE","Number":"A20"},{"entrance":"2019-06-28T11:19:10Z","status":"waiting","totalCharge":"0","user":{"$oid":"5d1cb530fc13ae462900017b"},"licencePlate":"B4680ZZP","Number":"A19"},{"entrance":"2019-06-28T10:45:40Z","status":"paid","totalCharge":"IDR22000","user":{"$oid":"5d1cb531fc13ae4629000191"},"licencePlate":"B8631YZO","Number":"A41"},{"entrance":"2019-06-28T05:05:54Z","status":"paid","totalCharge":"IDR69000","user":{"$oid":"5d1cb531fc13ae462900019d"},"licencePlate":"B6633IVY","Number":"A53"},{"entrance":"2019-06-28T03:18:16Z","status":"canceled","totalCharge":"-","user":{"$oid":"5d1cb531fc13ae46290001a3"},"licencePlate":"B3035BZQ","Number":"A59"},{"entrance":"2019-06-28T02:18:22Z","status":"paid","totalCharge":"IDR48000","user":{"$oid":"5d1cb531fc13ae46290001bf"},"licencePlate":"B1107LGM","Number":"A87"},{"entrance":"2019-06-28T00:43:37Z","status":"canceled","totalCharge":"-","user":{"$oid":"5d1cb531fc13ae46290001b3"},"licencePlate":"B2563EBZ","Number":"A75"},{"entrance":"2019-06-27T21:53:52Z","status":"paid","totalCharge":"IDR85000","user":{"$oid":"5d1cb531fc13ae46290001ce"},"licencePlate":"B8150GFY","Number":"B2"},{"entrance":"2019-06-27T20:42:57Z","status":"canceled","totalCharge":"-","user":{"$oid":"5d1cb531fc13ae4629000194"},"licencePlate":"B2346JDC","Number":"A44"},{"entrance":"2019-06-27T18:10:53Z","status":"canceled","totalCharge":"-","user":{"$oid":"5d1cb531fc13ae4629000215"},"licencePlate":"B6886HWC","Number":"B73"},{"entrance":"2019-06-27T13:39:59Z","status":"canceled","totalCharge":"-","user":{"$oid":"5d1cb531fc13ae46290001c6"},"licencePlate":"B0836PQR","Number":"A94"},{"entrance":"2019-06-27T09:20:10Z","status":"paid","totalCharge":"IDR31000","user":{"$oid":"5d1cb531fc13ae4629000193"},"licencePlate":"B7567NSW","Number":"A43"},{"entrance":"2019-06-27T08:22:33Z","status":"canceled","totalCharge":"-","user":{"$oid":"5d1cb531fc13ae462900020f"},"licencePlate":"B2458IMM","Number":"B67"},{"entrance":"2019-06-27T07:04:08Z","status":"paid","totalCharge":"IDR75000","user":{"$oid":"5d1cb531fc13ae4629000199"},"licencePlate":"B5523JOK","Number":"A49"},{"entrance":"2019-06-27T06:56:03Z","status":"paid","totalCharge":"IDR99000","user":{"$oid":"5d1cb530fc13ae4629000170"},"licencePlate":"B2801YQV","Number":"A8"},{"entrance":"2019-06-27T06:33:08Z","status":"paid","totalCharge":"IDR59000","user":{"$oid":"5d1cb531fc13ae462900019a"},"licencePlate":"B1663MVZ","Number":"A50"},{"entrance":"2019-06-27T05:46:41Z","status":"canceled","totalCharge":"-","user":{"$oid":"5d1cb531fc13ae46290001be"},"licencePlate":"B7376VSN","Number":"A86"},{"entrance":"2019-06-27T02:29:44Z","status":"paid","totalCharge":"IDR21000","user":{"$oid":"5d1cb531fc13ae46290001f4"},"licencePlate":"B7005BES","Number":"B40"},{"entrance":"2019-06-27T01:54:42Z","status":"paid","totalCharge":"IDR39000","user":{"$oid":"5d1cb530fc13ae462900018a"},"licencePlate":"B3861EFP","Number":"A34"},{"entrance":"2019-06-27T01:44:42Z","status":"canceled","totalCharge":"-","user":{"$oid":"5d1cb531fc13ae46290001a8"},"licencePlate":"B4048PVV","Number":"A64"},{"entrance":"2019-06-26T20:15:30Z","status":"canceled","totalCharge":"-","user":{"$oid":"5d1cb531fc13ae4629000198"},"licencePlate":"B4017TYE","Number":"A48"},{"entrance":"2019-06-26T15:06:18Z","status":"paid","totalCharge":"IDR61000","user":{"$oid":"5d1cb531fc13ae4629000206"},"licencePlate":"B6303TZK","Number":"B58"},{"entrance":"2019-06-26T08:42:37Z","status":"canceled","totalCharge":"-","user":{"$oid":"5d1cb531fc13ae46290001a5"},"licencePlate":"B7028PIM","Number":"A61"},{"entrance":"2019-06-26T06:58:08Z","status":"canceled","totalCharge":"-","user":{"$oid":"5d1cb531fc13ae4629000192"},"licencePlate":"B4200ENY","Number":"A42"},{"entrance":"2019-06-26T06:44:10Z","status":"waiting","totalCharge":"0","user":{"$oid":"5d1cb531fc13ae462900019f"},"licencePlate":"B0652GTF","Number":"A55"},{"entrance":"2019-06-25T22:14:13Z","status":"paid","totalCharge":"IDR65000","user":{"$oid":"5d1cb531fc13ae46290001ef"},"licencePlate":"B7801ORR","Number":"B35"},{"entrance":"2019-06-25T21:38:57Z","status":"paid","totalCharge":"IDR50000","user":{"$oid":"5d1cb531fc13ae46290001fe"},"licencePlate":"B3628RKT","Number":"B50"},{"entrance":"2019-06-25T21:22:47Z","status":"paid","totalCharge":"IDR86000","user":{"$oid":"5d1cb531fc13ae4629000203"},"licencePlate":"B0438HMO","Number":"B55"},{"entrance":"2019-06-25T20:52:39Z","status":"waiting","totalCharge":"0","user":{"$oid":"5d1cb531fc13ae46290001c9"},"licencePlate":"B1444KJS","Number":"A97"},{"entrance":"2019-06-25T20:42:23Z","status":"canceled","totalCharge":"-","user":{"$oid":"5d1cb531fc13ae46290001cf"},"licencePlate":"B1768EAV","Number":"B3"},{"entrance":"2019-06-25T19:30:15Z","status":"waiting","totalCharge":"0","user":{"$oid":"5d1cb530fc13ae4629000175"},"licencePlate":"B5038EXL","Number":"A13"},{"entrance":"2019-06-25T16:39:29Z","status":"waiting","totalCharge":"0","user":{"$oid":"5d1cb531fc13ae462900018e"},"licencePlate":"B1313YRY","Number":"A38"},{"entrance":"2019-06-25T11:58:29Z","status":"waiting","totalCharge":"0","user":{"$oid":"5d1cb531fc13ae462900020a"},"licencePlate":"B6020FEW","Number":"B62"},{"entrance":"2019-06-25T08:00:48Z","status":"paid","totalCharge":"IDR21000","user":{"$oid":"5d1cb531fc13ae462900021b"},"licencePlate":"B0635MJC","Number":"B79"},{"entrance":"2019-06-25T06:34:16Z","status":"waiting","totalCharge":"0","user":{"$oid":"5d1cb531fc13ae46290001fa"},"licencePlate":"B3102LCW","Number":"B46"},{"entrance":"2019-06-25T03:51:24Z","status":"waiting","totalCharge":"0","user":{"$oid":"5d1cb530fc13ae4629000174"},"licencePlate":"B1811WHM","Number":"A12"},{"entrance":"2019-06-24T22:38:21Z","status":"paid","totalCharge":"IDR24000","user":{"$oid":"5d1cb531fc13ae4629000197"},"licencePlate":"B0613RSP","Number":"A47"},{"entrance":"2019-06-24T21:49:47Z","status":"waiting","totalCharge":"0","user":{"$oid":"5d1cb530fc13ae4629000176"},"licencePlate":"B6401SPF","Number":"A14"},{"entrance":"2019-06-24T17:56:43Z","status":"paid","totalCharge":"IDR74000","user":{"$oid":"5d1cb531fc13ae46290001ff"},"licencePlate":"B4815AKO","Number":"B51"},{"entrance":"2019-06-24T15:31:09Z","status":"paid","totalCharge":"IDR89000","user":{"$oid":"5d1cb531fc13ae4629000205"},"licencePlate":"B1178SZR","Number":"B57"},{"entrance":"2019-06-24T14:32:32Z","status":"paid","totalCharge":"IDR48000","user":{"$oid":"5d1cb531fc13ae4629000212"},"licencePlate":"B0448HDP","Number":"B70"},{"entrance":"2019-06-24T13:42:13Z","status":"canceled","totalCharge":"-","user":{"$oid":"5d1cb531fc13ae46290001b2"},"licencePlate":"B2461MYW","Number":"A74"},{"entrance":"2019-06-24T13:06:42Z","status":"waiting","totalCharge":"0","user":{"$oid":"5d1cb531fc13ae46290001d8"},"licencePlate":"B4168GBA","Number":"B12"},{"entrance":"2019-06-24T12:08:26Z","status":"canceled","totalCharge":"-","user":{"$oid":"5d1cb531fc13ae462900020c"},"licencePlate":"B3162AGW","Number":"B64"},{"entrance":"2019-06-24T09:04:43Z","status":"waiting","totalCharge":"0","user":{"$oid":"5d1cb531fc13ae46290001ec"},"licencePlate":"B6534VRJ","Number":"B32"},{"entrance":"2019-06-24T07:41:33Z","status":"waiting","totalCharge":"0","user":{"$oid":"5d1cb531fc13ae4629000211"},"licencePlate":"B4367HCA","Number":"B69"},{"entrance":"2019-06-24T07:28:32Z","status":"waiting","totalCharge":"0","user":{"$oid":"5d1cb531fc13ae46290001da"},"licencePlate":"B8174NHL","Number":"B14"},{"entrance":"2019-06-24T07:10:37Z","status":"canceled","totalCharge":"-","user":{"$oid":"5d1cb531fc13ae4629000207"},"licencePlate":"B8271RAE","Number":"B59"},{"entrance":"2019-06-24T05:52:30Z","status":"canceled","totalCharge":"-","user":{"$oid":"5d1cb531fc13ae4629000195"},"licencePlate":"B6388PSI","Number":"A45"},{"entrance":"2019-06-24T05:23:35Z","status":"canceled","totalCharge":"-","user":{"$oid":"5d1cb531fc13ae462900020b"},"licencePlate":"B2421LGD","Number":"B63"},{"entrance":"2019-06-24T02:54:05Z","status":"paid","totalCharge":"IDR52000","user":{"$oid":"5d1cb531fc13ae46290001e0"},"licencePlate":"B6466FIL","Number":"B20"},{"entrance":"2019-06-24T02:42:22Z","status":"waiting","totalCharge":"0","user":{"$oid":"5d1cb530fc13ae462900017f"},"licencePlate":"B7853PSH","Number":"A23"},{"entrance":"2019-06-24T00:51:47Z","status":"paid","totalCharge":"IDR31000","user":{"$oid":"5d1cb531fc13ae46290001e1"},"licencePlate":"B7112LXJ","Number":"B21"},{"entrance":"2019-06-23T22:27:15Z","status":"waiting","totalCharge":"0","user":{"$oid":"5d1cb531fc13ae4629000204"},"licencePlate":"B2531XXA","Number":"B56"},{"entrance":"2019-06-23T17:54:06Z","status":"canceled","totalCharge":"-","user":{"$oid":"5d1cb530fc13ae4629000173"},"licencePlate":"B8566RRJ","Number":"A11"},{"entrance":"2019-06-23T17:00:11Z","status":"paid","totalCharge":"IDR32000","user":{"$oid":"5d1cb531fc13ae46290001ac"},"licencePlate":"B1228SDL","Number":"A68"},{"entrance":"2019-06-23T15:59:10Z","status":"paid","totalCharge":"IDR24000","user":{"$oid":"5d1cb531fc13ae46290001d5"},"licencePlate":"B1023FHX","Number":"B9"},{"entrance":"2019-06-23T13:42:43Z","status":"paid","totalCharge":"IDR27000","user":{"$oid":"5d1cb530fc13ae462900016e"},"licencePlate":"B6068OIL","Number":"A6"},{"entrance":"2019-06-23T12:56:57Z","status":"paid","totalCharge":"IDR66000","user":{"$oid":"5d1cb530fc13ae4629000187"},"licencePlate":"B8812OHX","Number":"A31"},{"entrance":"2019-06-23T11:50:26Z","status":"canceled","totalCharge":"-","user":{"$oid":"5d1cb531fc13ae46290001eb"},"licencePlate":"B4433DJS","Number":"B31"},{"entrance":"2019-06-23T10:53:55Z","status":"waiting","totalCharge":"0","user":{"$oid":"5d1cb530fc13ae4629000179"},"licencePlate":"B6366ARD","Number":"A17"},{"entrance":"2019-06-23T07:21:39Z","status":"waiting","totalCharge":"0","user":{"$oid":"5d1cb531fc13ae4629000209"},"licencePlate":"B7328VOX","Number":"B61"},{"entrance":"2019-06-23T07:14:49Z","status":"waiting","totalCharge":"0","user":{"$oid":"5d1cb531fc13ae462900018b"},"licencePlate":"B4713NZB","Number":"A35"},{"entrance":"2019-06-23T04:13:51Z","status":"paid","totalCharge":"IDR69000","user":{"$oid":"5d1cb531fc13ae46290001c3"},"licencePlate":"B0404PWE","Number":"A91"},{"entrance":"2019-06-23T00:54:32Z","status":"paid","totalCharge":"IDR66000","user":{"$oid":"5d1cb531fc13ae46290001f1"},"licencePlate":"B7703CWT","Number":"B37"},{"entrance":"2019-06-22T23:02:48Z","status":"waiting","totalCharge":"0","user":{"$oid":"5d1cb530fc13ae4629000186"},"licencePlate":"B6844PRM","Number":"A30"},{"entrance":"2019-06-22T18:25:03Z","status":"paid","totalCharge":"IDR36000","user":{"$oid":"5d1cb531fc13ae46290001d2"},"licencePlate":"B8043OFM","Number":"B6"},{"entrance":"2019-06-22T14:55:07Z","status":"waiting","totalCharge":"0","user":{"$oid":"5d1cb530fc13ae462900016c"},"licencePlate":"B5558VFZ","Number":"A4"},{"entrance":"2019-06-22T13:54:37Z","status":"waiting","totalCharge":"0","user":{"$oid":"5d1cb530fc13ae4629000183"},"licencePlate":"B3867NAZ","Number":"A27"},{"entrance":"2019-06-22T13:38:43Z","status":"waiting","totalCharge":"0","user":{"$oid":"5d1cb531fc13ae46290001ad"},"licencePlate":"B0712YYQ","Number":"A69"},{"entrance":"2019-06-22T11:46:26Z","status":"canceled","totalCharge":"-","user":{"$oid":"5d1cb531fc13ae46290001c7"},"licencePlate":"B3030FFO","Number":"A95"},{"entrance":"2019-06-22T09:32:42Z","status":"canceled","totalCharge":"-","user":{"$oid":"5d1cb530fc13ae4629000182"},"licencePlate":"B5260GFL","Number":"A26"},{"entrance":"2019-06-22T09:11:44Z","status":"canceled","totalCharge":"-","user":{"$oid":"5d1cb531fc13ae46290001f7"},"licencePlate":"B6881XJA","Number":"B43"},{"entrance":"2019-06-22T07:57:30Z","status":"paid","totalCharge":"IDR56000","user":{"$oid":"5d1cb531fc13ae46290001a6"},"licencePlate":"B5523TDM","Number":"A62"},{"entrance":"2019-06-22T07:11:30Z","status":"paid","totalCharge":"IDR58000","user":{"$oid":"5d1cb531fc13ae4629000202"},"licencePlate":"B8402BHC","Number":"B54"},{"entrance":"2019-06-22T05:26:11Z","status":"waiting","totalCharge":"0","user":{"$oid":"5d1cb530fc13ae462900016f"},"licencePlate":"B7407GIK","Number":"A7"},{"entrance":"2019-06-22T04:08:51Z","status":"waiting","totalCharge":"0","user":{"$oid":"5d1cb530fc13ae462900017e"},"licencePlate":"B5368SSK","Number":"A22"},{"entrance":"2019-06-22T02:09:24Z","status":"canceled","totalCharge":"-","user":{"$oid":"5d1cb531fc13ae46290001fc"},"licencePlate":"B5607JNX","Number":"B48"},{"entrance":"2019-06-22T00:19:55Z","status":"canceled","totalCharge":"-","user":{"$oid":"5d1cb531fc13ae46290001b1"},"licencePlate":"B7267QND","Number":"A73"},{"entrance":"2019-06-21T16:59:05Z","status":"paid","totalCharge":"IDR94000","user":{"$oid":"5d1cb531fc13ae46290001e2"},"licencePlate":"B8625XLZ","Number":"B22"},{"entrance":"2019-06-21T15:06:19Z","status":"paid","totalCharge":"IDR25000","user":{"$oid":"5d1cb531fc13ae46290001c1"},"licencePlate":"B7455YMI","Number":"A89"},{"entrance":"2019-06-21T10:17:04Z","status":"canceled","totalCharge":"-","user":{"$oid":"5d1cb531fc13ae46290001c2"},"licencePlate":"B0867HSQ","Number":"A90"},{"entrance":"2019-06-21T07:43:13Z","status":"paid","totalCharge":"IDR65000","user":{"$oid":"5d1cb531fc13ae46290001f2"},"licencePlate":"B6380QBX","Number":"B38"},{"entrance":"2019-06-21T07:19:13Z","status":"canceled","totalCharge":"-","user":{"$oid":"5d1cb531fc13ae46290001db"},"licencePlate":"B6537GKY","Number":"B15"},{"entrance":"2019-06-21T04:12:12Z","status":"paid","totalCharge":"IDR91000","user":{"$oid":"5d1cb531fc13ae4629000216"},"licencePlate":"B7103SPY","Number":"B74"},{"entrance":"2019-06-21T03:25:48Z","status":"paid","totalCharge":"IDR63000","user":{"$oid":"5d1cb531fc13ae46290001f3"},"licencePlate":"B7552HSW","Number":"B39"},{"entrance":"2019-06-21T02:49:16Z","status":"canceled","totalCharge":"-","user":{"$oid":"5d1cb531fc13ae46290001d6"},"licencePlate":"B7700CZV","Number":"B10"},{"entrance":"2019-06-21T01:36:56Z","status":"paid","totalCharge":"IDR72000","user":{"$oid":"5d1cb530fc13ae4629000180"},"licencePlate":"B7777EYZ","Number":"A24"}]